dailylog_lib/__init__.py
dailylog_lib/cache.py
dailylog_lib/config.py
dailylog_lib/constants.py
dailylog_lib/exceptions.py
dailylog_lib/foos.py
dailylog_lib/logger.py
dailylog_lib/options.py
dailylog_lib/py.typed
dailylog_lib-0.2.3.dist-info/LICENSE
dailylog_lib-0.2.3.dist-info/METADATA
dailylog_lib-0.2.3.dist-info/WHEEL
dailylog_lib-0.2.3.dist-info/RECORD
