Metadata-Version: 2.3
Name: dailylog-lib
Version: 0.2.3
Summary: A minimal logger that will suppress all but first message in a specified time to screen
Author: Quien Sabe
Author-email: qs5779@mail.com
Requires-Python: >=3.10,<4.0
Classifier: Development Status :: 3 - Alpha
Classifier: Operating System :: POSIX :: Linux
Classifier: Programming Language :: Python :: 3
Classifier: Programming Language :: Python :: 3.10
Classifier: Programming Language :: Python :: 3.11
Classifier: Programming Language :: Python :: 3.12
Classifier: Programming Language :: Python :: 3.13
Classifier: Programming Language :: Python :: 3 :: Only
Classifier: Typing :: Typed
Requires-Dist: wtforglib (>=1.1.1,<2.0.0)
